qunfold/__init__.py
qunfold/qplotter.py
qunfold/qunfolder.py
qunfold/root2numpy.py
qunfold/utils.py
QUnfold-0.3.5.dist-info/LICENSE
QUnfold-0.3.5.dist-info/METADATA
QUnfold-0.3.5.dist-info/WHEEL
QUnfold-0.3.5.dist-info/top_level.txt
QUnfold-0.3.5.dist-info/RECORD
