Metadata-Version: 2.1
Name: QUnfold
Version: 0.3.5
Summary: A quantum-based approach to the distribution unfolding problem
Author-email: Gianluca Bianco <biancogianluca9@gmail.com>, Simone Gasperini <simone.gasperini4@unibo.it>
License: MIT
Project-URL: Homepage, https://github.com/Quantum4HEP/QUnfold
Project-URL: Documentation, https://qunfold.readthedocs.io/en/latest/
Keywords: quantum,annealing,unfolding,statistics,python
Classifier: Programming Language :: Python :: 3
Classifier: License :: OSI Approved :: MIT License
Classifier: Operating System :: POSIX :: Linux
Classifier: Operating System :: MacOS
Classifier: Intended Audience :: Science/Research
Classifier: Topic :: Scientific/Engineering
Requires-Python: >=3.9
License-File: LICENSE
Requires-Dist: numpy
Requires-Dist: scipy
Requires-Dist: jax
Requires-Dist: matplotlib
Requires-Dist: dwave-ocean-sdk
Requires-Dist: scikit-learn
Requires-Dist: tqdm
Provides-Extra: gurobi
Requires-Dist: gurobipy; extra == "gurobi"
